AUTHORS
LICENSE
MANIFEST.in
README.md
pyproject.toml
setup.py
csrc/selective_scan/reverse_scan.cuh
csrc/selective_scan/selective_scan.cpp
csrc/selective_scan/selective_scan.h
csrc/selective_scan/selective_scan_bwd_bf16_complex.cu
csrc/selective_scan/selective_scan_bwd_bf16_real.cu
csrc/selective_scan/selective_scan_bwd_fp16_complex.cu
csrc/selective_scan/selective_scan_bwd_fp16_real.cu
csrc/selective_scan/selective_scan_bwd_fp32_complex.cu
csrc/selective_scan/selective_scan_bwd_fp32_real.cu
csrc/selective_scan/selective_scan_bwd_kernel.cuh
csrc/selective_scan/selective_scan_common.h
csrc/selective_scan/selective_scan_fwd_bf16.cu
csrc/selective_scan/selective_scan_fwd_fp16.cu
csrc/selective_scan/selective_scan_fwd_fp32.cu
csrc/selective_scan/selective_scan_fwd_kernel.cuh
csrc/selective_scan/static_switch.h
csrc/selective_scan/uninitialized_copy.cuh
mamba_ssm/__init__.py
mamba_ssm.egg-info/PKG-INFO
mamba_ssm.egg-info/SOURCES.txt
mamba_ssm.egg-info/dependency_links.txt
mamba_ssm.egg-info/requires.txt
mamba_ssm.egg-info/top_level.txt
mamba_ssm/distributed/__init__.py
mamba_ssm/distributed/distributed_utils.py
mamba_ssm/distributed/tensor_parallel.py
mamba_ssm/models/__init__.py
mamba_ssm/models/config_mamba.py
mamba_ssm/models/mixer_seq_simple.py
mamba_ssm/modules/__init__.py
mamba_ssm/modules/block.py
mamba_ssm/modules/mamba2.py
mamba_ssm/modules/mamba2_simple.py
mamba_ssm/modules/mamba_simple.py
mamba_ssm/modules/mha.py
mamba_ssm/modules/mlp.py
mamba_ssm/modules/ssd_minimal.py
mamba_ssm/ops/__init__.py
mamba_ssm/ops/selective_scan_interface.py
mamba_ssm/ops/triton/__init__.py
mamba_ssm/ops/triton/k_activations.py
mamba_ssm/ops/triton/layer_norm.py
mamba_ssm/ops/triton/layernorm_gated.py
mamba_ssm/ops/triton/selective_state_update.py
mamba_ssm/ops/triton/softplus.py
mamba_ssm/ops/triton/ssd_bmm.py
mamba_ssm/ops/triton/ssd_chunk_scan.py
mamba_ssm/ops/triton/ssd_chunk_state.py
mamba_ssm/ops/triton/ssd_combined.py
mamba_ssm/ops/triton/ssd_state_passing.py
mamba_ssm/utils/__init__.py
mamba_ssm/utils/generation.py
mamba_ssm/utils/hf.py
mamba_ssm/utils/torch.py