Metadata-Version: 2.1
Name: mamba-ssm
Version: 2.2.6.post3
Summary: Mamba state-space model
Home-page: https://github.com/state-spaces/mamba
Author: Tri Dao, Albert Gu
Author-email: Tri Dao <tri@tridao.me>, Albert Gu <agu@cs.cmu.edu>
License:                                  Apache License
Project-URL: Repository, https://github.com/state-spaces/mamba
Keywords: cuda,pytorch,state-space model
Classifier: Programming Language :: Python :: 3
Classifier: License :: OSI Approved :: Apache Software License
Classifier: Operating System :: Unix
Requires-Python: >=3.9
Provides-Extra: causal-conv1d
Provides-Extra: dev
License-File: LICENSE
License-File: AUTHORS
